akridata_dsp/__init__.py
akridata_dsp/api_client.py
akridata_dsp/configuration.py
akridata_dsp/exceptions.py
akridata_dsp/rest.py
akridata_dsp/api/__init__.py
akridata_dsp/api/anomaly_segmentation_api.py
akridata_dsp/api/catalog_source_tag_api.py
akridata_dsp/api/cluster_snapshot_api.py
akridata_dsp/api/coresets_api.py
akridata_dsp/api/customers_api.py
akridata_dsp/api/dataset_api.py
akridata_dsp/api/entity_api.py
akridata_dsp/api/er_update_annotations_state_api.py
akridata_dsp/api/expert_review_stats_api.py
akridata_dsp/api/get_annotations_count_api.py
akridata_dsp/api/get_er_annotations_count_api.py
akridata_dsp/api/get_er_review_state_count_api.py
akridata_dsp/api/health_api.py
akridata_dsp/api/image_fetch_api.py
akridata_dsp/api/image_server_api.py
akridata_dsp/api/image_tags_api.py
akridata_dsp/api/images_api.py
akridata_dsp/api/job_requests_api.py
akridata_dsp/api/label_instructions_api.py
akridata_dsp/api/labelspec_api.py
akridata_dsp/api/model_training_api.py
akridata_dsp/api/multi_class_stats_api.py
akridata_dsp/api/request_api.py
akridata_dsp/api/request_statistics_api.py
akridata_dsp/api/resultset_api.py
akridata_dsp/api/saliency_map_api.py
akridata_dsp/api/scenario_api.py
akridata_dsp/api/scenario_execution_api.py
akridata_dsp/api/sim_search_request_v1_api.py
akridata_dsp/api/sim_search_request_v2_api.py
akridata_dsp/api/summary_stats_api.py
akridata_dsp/api/synthesis_api.py
akridata_dsp/api/tag_api.py
akridata_dsp/api/top_class_stats_api.py
akridata_dsp/api/update_annotations_state_api.py
akridata_dsp/api/video_api.py
akridata_dsp/models/__init__.py
akridata_dsp/models/access_type.py
akridata_dsp/models/add.py
akridata_dsp/models/add_dataset.py
akridata_dsp/models/add_tags_request.py
akridata_dsp/models/add_test_image_status.py
akridata_dsp/models/add_test_images_request.py
akridata_dsp/models/akriad_post_rules_rule_operator.py
akridata_dsp/models/akrimanager_pipeline_types.py
akridata_dsp/models/analyse_submit_request.py
akridata_dsp-2.16.0.dev0.dist-info/METADATA
akridata_dsp-2.16.0.dev0.dist-info/WHEEL
akridata_dsp-2.16.0.dev0.dist-info/top_level.txt
akridata_dsp-2.16.0.dev0.dist-info/RECORD
