Metadata-Version: 2.1
Name: akridata_dsp
Version: 2.16.0.dev0
Summary: DSP Backend
Home-page: 
Author: OpenAPI Generator community
Author-email: team@openapitools.org
Keywords: OpenAPI,OpenAPI-Generator,DSP Backend
Requires-Dist: urllib3 (>=1.25.3)
Requires-Dist: six (>=1.10)
Requires-Dist: python-dateutil
